LICENSE
MANIFEST.in
README.md
setup.cfg
setup.py
tap_codat/__init__.py
tap_codat/context.py
tap_codat/http.py
tap_codat/state.py
tap_codat/streams.py
tap_codat/transform.py
tap_codat.egg-info/PKG-INFO
tap_codat.egg-info/SOURCES.txt
tap_codat.egg-info/dependency_links.txt
tap_codat.egg-info/entry_points.txt
tap_codat.egg-info/requires.txt
tap_codat.egg-info/top_level.txt
tap_codat/schemas/accounts.json
tap_codat/schemas/balance_sheets.json
tap_codat/schemas/bank_account_transactions.json
tap_codat/schemas/bank_accounts.json
tap_codat/schemas/bank_statement_lines.json
tap_codat/schemas/bank_statements.json
tap_codat/schemas/bill_payments.json
tap_codat/schemas/bills.json
tap_codat/schemas/companies.json
tap_codat/schemas/company_info.json
tap_codat/schemas/connections.json
tap_codat/schemas/credit_notes.json
tap_codat/schemas/customers.json
tap_codat/schemas/events.json
tap_codat/schemas/flattened_report.json
tap_codat/schemas/invoices.json
tap_codat/schemas/items.json
tap_codat/schemas/journal_entries.json
tap_codat/schemas/payment_allocations.json
tap_codat/schemas/payments.json
tap_codat/schemas/profit_and_loss.json
tap_codat/schemas/suppliers.json
tap_codat/schemas/tax_rates.json
test/test_report_flattening.py